{"c_deps": {}, "m_deps": {}, "full_fm": "package com.google.gson.metrics;\n\n\npublic class BagOfPrimitives{\npublic  BagOfPrimitives()\npublic  BagOfPrimitives(long longValue, int intValue, boolean booleanValue, String stringValue)\npublic static final long DEFAULT_VALUE = 0;\npublic long longValue;\npublic int intValue;\npublic boolean booleanValue;\npublic String stringValue;\npublic int getIntValue()\n@Override\n  public boolean equals(Object obj) {\n    if (this == obj) return true;\n    if (obj == null) return false;\n    if (getClass() != obj.getClass()) return false;\n    BagOfPrimitives other = (BagOfPrimitives) obj;\n    if (booleanValue != other.booleanValue) return false;\n    if (intValue != other.intValue) return false;\n    if (longValue != other.longValue) return false;\n    if (stringValue == null) {\n      return other.stringValue == null;\n    } else {\n      return stringValue.equals(other.stringValue);\n    }\n  }\n}", "focal_method": "@Override public boolean equals(Object obj)", "class_name": "BagOfPrimitives"}