{"c_deps": {}, "m_deps": {}, "full_fm": "package com.google.gson;\n\nimport com.google.gson.internal.LinkedTreeMap;\nimport java.util.Map;\nimport java.util.Set;\npublic final class JsonObject extends JsonElement{\n@SuppressWarnings(\"deprecation\") // superclass constructor public  JsonObject()\nprivate final LinkedTreeMap<String, JsonElement> members = new LinkedTreeMap<>(false);\npublic Map<String, JsonElement> asMap()\npublic void add(String property, JsonElement value) {\n    members.put(property, value == null ? JsonNull.INSTANCE : value);\n  }\n}", "focal_method": "public void add(String property, JsonElement value)", "class_name": "JsonObject"}