{"c_deps": {}, "m_deps": {}, "full_fm": "package com.google.gson;\n\nimport com.google.gson.internal.LazilyParsedNumber;\nimport java.math.BigDecimal;\nimport java.math.BigInteger;\nimport java.util.Objects;\npublic final class JsonPrimitive extends JsonElement{\n@SuppressWarnings(\"deprecation\") // superclass constructor public  JsonPrimitive(Boolean bool)\n@SuppressWarnings(\"deprecation\") // superclass constructor public  JsonPrimitive(Number number)\n@SuppressWarnings(\"deprecation\") // superclass constructor public  JsonPrimitive(String string)\n@SuppressWarnings(\"deprecation\") // superclass constructor public  JsonPrimitive(Character c)\nprivate final Object value;\n@Override\n  public int hashCode() {\n    if (value == null) {\n      return 31;\n    }\n    // Using recommended hashing algorithm from Effective Java for longs and doubles\n    if (isIntegral(this)) {\n      long value = getAsNumber().longValue();\n      return (int) (value ^ (value >>> 32));\n    }\n    if (value instanceof Number) {\n      long value = Double.doubleToLongBits(getAsNumber().doubleValue());\n      return (int) (value ^ (value >>> 32));\n    }\n    return value.hashCode();\n  }\n@Override public Number getAsNumber()\n}", "focal_method": "@Override public int hashCode()", "class_name": "JsonPrimitive"}