{"id": 481, "project_name": "gson", "signature": "@Override public boolean retainAll(Collection<?> c)", "method_name": "retainAll", "parameters": "retainAll(Collection<?>)", "source_code": "@Override public boolean retainAll(Collection<?> c) {\n    return delegate.retainAll(c);\n  }", "class_name": "NonNullElementWrapperList", "dependencies": {"ArrayList<E>": ["retainAll(Collection<?>)"]}, "use_field": 1, "is_constructor": 0, "is_get_set": 0, "is_public": 1, "package": "package com.google.gson.internal;", "imports": "import java.util.AbstractList;\nimport java.util.ArrayList;\nimport java.util.Collection;\nimport java.util.List;\nimport java.util.Objects;\nimport java.util.RandomAccess;"}