{"id": 496, "project_name": "gson", "signature": "public static TypeAdapterFactory newFactoryWithMatchRawType(\n      TypeToken<?> exactType, Object typeAdapter)", "method_name": "newFactoryWithMatchRawType", "parameters": "newFactoryWithMatchRawType(TypeToken<?>, Object)", "source_code": "public static TypeAdapterFactory newFactoryWithMatchRawType(\n      TypeToken<?> exactType, Object typeAdapter) {\n    // only bother matching raw types if exact type is a raw type\n    boolean matchRawType = exactType.getType() == exactType.getRawType();\n    return new SingleTypeFactory(typeAdapter, exactType, matchRawType, null);\n  }", "class_name": "TreeTypeAdapter", "dependencies": {"TypeToken<?>": ["getType()", "getRawType()"]}, "use_field": 0, "is_constructor": 0, "is_get_set": 0, "is_public": 1, "package": "package com.google.gson.internal.bind;", "imports": "import com.google.gson.Gson;\nimport com.google.gson.JsonDeserializationContext;\nimport com.google.gson.JsonDeserializer;\nimport com.google.gson.JsonElement;\nimport com.google.gson.JsonParseException;\nimport com.google.gson.JsonSerializationContext;\nimport com.google.gson.JsonSerializer;\nimport com.google.gson.TypeAdapter;\nimport com.google.gson.TypeAdapterFactory;\nimport com.google.gson.internal.$Gson$Preconditions;\nimport com.google.gson.internal.Streams;\nimport com.google.gson.reflect.TypeToken;\nimport com.google.gson.stream.JsonReader;\nimport com.google.gson.stream.JsonWriter;\nimport java.io.IOException;\nimport java.lang.reflect.Type;"}